deepirtools/__init__.py
deepirtools/base.py
deepirtools/data.py
deepirtools/figures.py
deepirtools/iwave.py
deepirtools/models.py
deepirtools/settings.py
deepirtools/utils.py
deepirtools/data/cov_mat.csv
deepirtools/data/data.csv
deepirtools/data/factor_scores.csv
deepirtools/data/intercepts.csv
deepirtools/data/loadings.csv
deepirtools-0.2.1.dist-info/LICENSE
deepirtools-0.2.1.dist-info/METADATA
deepirtools-0.2.1.dist-info/WHEEL
deepirtools-0.2.1.dist-info/top_level.txt
deepirtools-0.2.1.dist-info/RECORD
