Metadata-Version: 2.1
Name: deepirtools
Version: 0.2.1
Summary: Deep learning-based estimation and inference for item response theory models.
Project-URL: Homepage, https://github.com/cjurban/deepirtools
Keywords: deep learning,item response theory,factor analysis
Requires-Python: >=3.7
License-File: LICENSE
Requires-Dist: torch
Requires-Dist: pyro-ppl
Requires-Dist: numpy
